Metadata-Version: 1.1
Name: github-email-explorer
Version: 0.2.7
Summary: A tool to get email addresses by action types such as starred, watching or fork on GitHub repositories; Send email content to those addresses with a template.
Home-page: https://github.com/yuecen/github-email-explorer
Author: yuecen
Author-email: yuecendev+pypi@gmail.com
License: MIT
Keywords: github,email,sendgrid,marketing
Platform: UNKNOWN
Classifier: Intended Audience :: Developers
Classifier: Programming Language :: Python
Classifier: Topic :: Communications :: Email
Classifier: Topic :: Software Development :: Libraries :: Python Modules
